alpaca_trade_api/__init__.py
alpaca_trade_api/__main__.py
alpaca_trade_api/common.py
alpaca_trade_api/entity.py
alpaca_trade_api/entity_v2.py
alpaca_trade_api/rest.py
alpaca_trade_api/rest_async.py
alpaca_trade_api/stream.py
alpaca_trade_api-3.1.1.dist-info/LICENSE
alpaca_trade_api-3.1.1.dist-info/METADATA
alpaca_trade_api-3.1.1.dist-info/NOTICE
alpaca_trade_api-3.1.1.dist-info/WHEEL
alpaca_trade_api-3.1.1.dist-info/top_level.txt
alpaca_trade_api-3.1.1.dist-info/RECORD
