Metadata-Version: 2.1
Name: alpaca-trade-api
Version: 3.1.1
Summary: Alpaca API python client
Home-page: https://github.com/alpacahq/alpaca-trade-api-python
Author: Alpaca
Author-email: oss@alpaca.markets
Keywords: financial,timeseries,api,trade
License-File: LICENSE
License-File: NOTICE
Requires-Dist: pandas>=0.18.1
Requires-Dist: numpy>=1.11.1
Requires-Dist: requests<3,>2
Requires-Dist: urllib3<2,>1.24
Requires-Dist: websocket-client<2,>=0.56.0
Requires-Dist: websockets<11,>=9.0
Requires-Dist: msgpack==1.0.3
Requires-Dist: aiohttp==3.8.2
Requires-Dist: PyYAML==6.0.1
Requires-Dist: deprecation==2.1.0
